loko_client/__init__.py
loko_client/apps/__init__.py
loko_client/business/__init__.py
loko_client/business/async_predictor_client.py
loko_client/business/base_client.py
loko_client/business/fs_client.py
loko_client/business/predictor_client.py
loko_client/business/projects_client.py
loko_client/config/AppConfig.py
loko_client/config/__init__.py
loko_client/dao/__init__.py
loko_client/examples/__init__.py
loko_client/model/__init__.py
loko_client/model/projects.py
loko_client/resources/__init__.py
loko_client/services/__init__.py
loko_client/services/services.py
loko_client/test/__init__.py
loko_client/test/asyncfsclient.py
loko_client/test/asyncpredictorclient.py
loko_client/test/fsclient.py
loko_client/test/pclient.py
loko_client/test/predictorclient.py
loko_client/utils/__init__.py
loko_client/utils/gobjects_utils.py
loko_client/utils/logger_utils.py
loko_client/utils/requests_utils.py
loko_client-0.0.1.dev3.dist-info/METADATA
loko_client-0.0.1.dev3.dist-info/WHEEL
loko_client-0.0.1.dev3.dist-info/top_level.txt
loko_client-0.0.1.dev3.dist-info/RECORD
