Metadata-Version: 2.1
Name: loko-client
Version: 0.0.1.dev3
Summary: A client for Loko orchestrator services
Author: Live Tech
Author-email: f.dantonio@ilivetech.it
Classifier: Programming Language :: Python :: 3
Classifier: License :: OSI Approved :: MIT License
Classifier: Operating System :: OS Independent
Requires-Python: >3.5.0
Requires-Dist: aiohttp
Requires-Dist: requests
